clicnet/__init__.py
clicnet/cancer_data.py
clicnet/clicnet.py
clicnet/rbm.py
clicnet/cdata/liu.pickle
clicnet/cdata/msk.pickle
clicnet/cdata/msktmb.pickle
clicnet/cdata/mut_profiles.pickle
clicnet/cdata/riaz.pickle
clicnet/cdata/tcga.pickle
clicnet-1.2.dist-info/LICENSE
clicnet-1.2.dist-info/METADATA
clicnet-1.2.dist-info/WHEEL
clicnet-1.2.dist-info/top_level.txt
clicnet-1.2.dist-info/RECORD
