Metadata-Version: 2.1
Name: clicnet
Version: 1.2
Summary: Clinical Clustering of Cancer patients based on neural NETworks (CLICnet).
Home-page: http://clicnet.pythonanywhere.com
Author: Ayal B. Gussow, Noam Auslander
Author-email: ayal.gussow@gmail.com, noamaus@gmail.com
License: UNKNOWN
Platform: UNKNOWN
Classifier: Programming Language :: Python :: 3
Classifier: License :: OSI Approved :: GNU General Public License (GPL)
Classifier: Operating System :: OS Independent
Requires-Python: >=3.6
Requires-Dist: numpy (>=1.17.3)
Requires-Dist: pandas (>=1.0.3)
Requires-Dist: lifelines (>=0.24.9)
Requires-Dist: seaborn (>=0.11.0)
Requires-Dist: matplotlib (>=3.3.1)
Requires-Dist: numexpr (>=2.7.1)
